faceblocker/__init__.py
faceblocker/deface.py
faceblocker/models/__init__.py
faceblocker/models/face_detection_yunet_2023mar.onnx
faceblocker-0.0.4.dist-info/LICENCE
faceblocker-0.0.4.dist-info/METADATA
faceblocker-0.0.4.dist-info/WHEEL
faceblocker-0.0.4.dist-info/entry_points.txt
faceblocker-0.0.4.dist-info/top_level.txt
faceblocker-0.0.4.dist-info/RECORD
