Metadata-Version: 2.1
Name: faceblocker
Version: 0.0.4
Summary: A CLI tool that can remove faces from videos and replace them with images.
Author-email: Rita Collins <r.collins3730@gmail.com>
Project-URL: Homepage, https://gitlab.com/rdotcollins/movie-anonymiser
Project-URL: Bug Tracker, https://gitlab.com/rdotcollins/movie-anonymiser/issues
Classifier: Programming Language :: Python :: 3
Classifier: License :: OSI Approved :: MIT License
Classifier: Operating System :: OS Independent
Requires-Python: >=3.11
License-File: LICENCE
Requires-Dist: moviepy <2.0
Requires-Dist: opencv-python >4.8.0
